gorillacompression/__init__.py
gorillacompression/decode.py
gorillacompression/encode.py
gorillacompression/result.py
gorillacompression/timestamps/__init__.py
gorillacompression/timestamps/constants.py
gorillacompression/timestamps/decode.py
gorillacompression/timestamps/encode.py
gorillacompression/timestamps/result.py
gorillacompression/values/__init__.py
gorillacompression/values/constants.py
gorillacompression/values/decode.py
gorillacompression/values/encode.py
gorillacompression/values/result.py
gorillacompression-1.0.2.dist-info/licenses/LICENSE
gorillacompression-1.0.2.dist-info/METADATA
gorillacompression-1.0.2.dist-info/WHEEL
gorillacompression-1.0.2.dist-info/top_level.txt
gorillacompression-1.0.2.dist-info/RECORD
