Metadata-Version: 2.4
Name: gorillacompression
Version: 1.0.2
Summary: Python implementation of Gorilla time series compression
Author-email: Ghiles Meddour <ghiles.meddour.b@gmail.com>
Project-URL: Repository, https://github.com/ghilesmeddour/gorilla-time-series-compression
Project-URL: Documentation, https://github.com/ghilesmeddour/gorilla-time-series-compression
Project-URL: Changelog, https://github.com/ghilesmeddour/gorilla-time-series-compression/blob/main/CHANGELOG.md
Project-URL: Releases, https://github.com/ghilesmeddour/gorilla-time-series-compression/releases
Requires-Python: >=3.9
License-File: LICENSE
Requires-Dist: bitarray>=3.0.0
Provides-Extra: dev
Requires-Dist: coverage>=7.8.0; extra == "dev"
Requires-Dist: devtools>=0.12.2; extra == "dev"
Requires-Dist: pytest>=8.3.5; extra == "dev"
Requires-Dist: ruff>=0.11.4; extra == "dev"
Requires-Dist: numpy>=2.0.0; extra == "dev"
Dynamic: license-file
